{
  "id": "vhir-species",
  "title": "VHIR Species Value Set",
  "description": "Common veterinary species. Use NCBI Taxonomy ID as code where possible.",
  "url": "https://vhir.dev/valuesets/species",
  "version": "0.1.0",
  "concepts": [
    { "code": "canis-familiaris",   "display": "Dog (Canis lupus familiaris)",  "ncbiTaxon": "9615",  "commonGroup": "companion" },
    { "code": "felis-catus",        "display": "Cat (Felis catus)",             "ncbiTaxon": "9685",  "commonGroup": "companion" },
    { "code": "equus-caballus",     "display": "Horse (Equus caballus)",        "ncbiTaxon": "9796",  "commonGroup": "equine" },
    { "code": "equus-asinus",       "display": "Donkey (Equus asinus)",         "ncbiTaxon": "9793",  "commonGroup": "equine" },
    { "code": "bos-taurus",         "display": "Cattle / Bovine (Bos taurus)", "ncbiTaxon": "9913",  "commonGroup": "livestock" },
    { "code": "bos-indicus",        "display": "Zebu / Bos indicus",           "ncbiTaxon": "9915",  "commonGroup": "livestock" },
    { "code": "sus-scrofa",         "display": "Pig (Sus scrofa)",             "ncbiTaxon": "9823",  "commonGroup": "livestock" },
    { "code": "ovis-aries",         "display": "Sheep (Ovis aries)",           "ncbiTaxon": "9940",  "commonGroup": "livestock" },
    { "code": "capra-hircus",       "display": "Goat (Capra hircus)",          "ncbiTaxon": "9925",  "commonGroup": "livestock" },
    { "code": "gallus-gallus",      "display": "Chicken (Gallus gallus)",      "ncbiTaxon": "9031",  "commonGroup": "poultry" },
    { "code": "meleagris-gallopavo","display": "Turkey",                        "ncbiTaxon": "9103",  "commonGroup": "poultry" },
    { "code": "anas-platyrhynchos", "display": "Duck",                         "ncbiTaxon": "8839",  "commonGroup": "poultry" },
    { "code": "oryctolagus-cuniculus","display": "Rabbit",                     "ncbiTaxon": "9986",  "commonGroup": "small-mammal" },
    { "code": "mesocricetus-auratus","display": "Hamster (Syrian)",            "ncbiTaxon": "10036", "commonGroup": "small-mammal" },
    { "code": "rattus-norvegicus",  "display": "Rat",                          "ncbiTaxon": "10116", "commonGroup": "small-mammal" },
    { "code": "mus-musculus",       "display": "Mouse",                        "ncbiTaxon": "10090", "commonGroup": "small-mammal" },
    { "code": "cavia-porcellus",    "display": "Guinea pig",                   "ncbiTaxon": "10141", "commonGroup": "small-mammal" },
    { "code": "chinchilla-lanigera","display": "Chinchilla",                   "ncbiTaxon": "34839", "commonGroup": "small-mammal" },
    { "code": "psittaciformes",     "display": "Parrot / Psittacine (order)",  "ncbiTaxon": "9223",  "commonGroup": "avian" },
    { "code": "columbiformes",      "display": "Pigeon / Dove (order)",        "ncbiTaxon": "8930",  "commonGroup": "avian" },
    { "code": "iguana-iguana",      "display": "Green iguana",                 "ncbiTaxon": "42514", "commonGroup": "reptile" },
    { "code": "serpentes",          "display": "Snake (suborder)",             "ncbiTaxon": "8570",  "commonGroup": "reptile" },
    { "code": "chelonia",           "display": "Turtle / Tortoise (order)",    "ncbiTaxon": "8459",  "commonGroup": "reptile" },
    { "code": "lama-glama",         "display": "Llama",                        "ncbiTaxon": "9844",  "commonGroup": "camelid" },
    { "code": "vicugna-pacos",      "display": "Alpaca",                       "ncbiTaxon": "30538", "commonGroup": "camelid" },
    { "code": "cervus-elaphus",     "display": "Red deer / Elk",               "ncbiTaxon": "9860",  "commonGroup": "cervid" },
    { "code": "bison-bison",        "display": "American bison",               "ncbiTaxon": "9901",  "commonGroup": "livestock" },
    { "code": "unknown",            "display": "Unknown / Mixed",              "ncbiTaxon": null,    "commonGroup": "other" }
  ]
}
